{
  "$schema": "https://aka.ms/terminal-profiles-schema",
  "defaultProfile": "{61c54bbd-c2c6-5271-96e7-009a87ff44bf}",
  "copyOnSelect": false,
  "copyFormatting": false,
  "theme": "dark",
  "profiles": {
    "defaults": {
    },
    "list": [
      {
        "guid": "{61c54bbd-c2c6-5271-96e7-009a87ff44bf}",
        "name": "Windows PowerShell⚡",
        "commandline": "powershell.exe",
        "colorScheme": "Retro",
        "cursorColor": "#FFFFFF",
        "cursorShape": "filledBox",
        "fontSize": 11,
        "fontFace": "Cascadia Code",
        "padding": "5, 5, 5, 5",
        "tabTitle": "Command Prompt",
        "hidden": false,
        "acrylicOpacity": 0.75,
        "useAcrylic": true,
        "startingDirectory": "E:\\Projects\\project-github",
        "experimental.retroTerminalEffect": true
      },
      {
        "guid": "{0caa0dad-35be-5f56-a8ff-afceeeaa6101}",
        "name": "Command Prompt",
        "commandline": "cmd.exe",
        "colorScheme": "Campbell",
        "hidden": false,
        "acrylicOpacity": 0.75,
        "useAcrylic": true,
        "fontSize": 11,
        "fontFace": "Cascadia Code"
      },
      {
        "guid": "{b453ae62-4e3d-5e58-b989-0a998ec441b8}",
        "hidden": false,
        "name": "Azure Cloud Shell",
        "source": "Windows.Terminal.Azure",
        "colorScheme": "One Half Dark",
        "acrylicOpacity": 0.75,
        "useAcrylic": true,
        "fontSize": 11,
        "fontFace": "Cascadia Code"
      },
      {
        "guid": "{c6eaf9f4-32a7-5fdc-b5cf-066e8a4b1e40}",
        "hidden": false,
        "name": "Ubuntu-18.04",
        "source": "Windows.Terminal.Wsl",
        "colorScheme": "Ubuntu 18.04",
        "acrylicOpacity": 0.75,
        "useAcrylic": true,
        "icon": "ms-appdata:///roaming/ubuntu_icon.png"
      },
      {
        "tabTitle": "Git Bash",
        "acrylicOpacity": 0.75,
        "closeOnExit": true,
        "colorScheme": "WildCherry",
        "commandline": "C:/Program Files/Git/bin/bash.exe --login",
        "cursorColor": "#FFFFFF",
        "cursorShape": "bar",
        "fontFace": "Cascadia Code",
        "fontSize": 12,
        "guid": "{14ad203f-52cc-4110-90d6-d96e0f41b64d}",
        "historySize": 9001,
        "name": "Git Bash🌈",
        "padding": "0, 0, 0, 0",
        "snapOnInput": true,
        "useAcrylic": true,
        "icon": "C:\\Users\\pangy\\AppData\\Roaming\\images\\git.png",
        "startingDirectory": "E:\\Projects\\project-github"
      },
      {
        "guid": "{07b52e3e-de2c-5db4-bd2d-ba144ed6c273}",
        "hidden": false,
        "name": "Ubuntu-20.04",
        "source": "Windows.Terminal.Wsl",
        "acrylicOpacity": 0.75,
        "useAcrylic": true,
        "colorScheme": "Raspberry",
        "cursorColor": "#FFFFFF",
        "fontFace": "Cascadia Code",
        "padding": "5, 5, 5, 5",
        "suppressApplicationTitle": true,
        "tabTitle": "Ubuntu"
      }
    ]
  },
  "schemes": [
    {
      "name": "Ubuntu 18.04",
      "foreground": "#CCCCCC",
      "background": "#300A24",
      "cursorColor": "#FFFFFF",
      "black": "#0C0C0C",
      "red": "#C50F1F",
      "green": "#13A10E",
      "yellow": "#C19C00",
      "blue": "#0037DA",
      "purple": "#881798",
      "cyan": "#3A96DD",
      "white": "#CCCCCC",
      "brightBlack": "#767676",
      "brightRed": "#E74856",
      "brightGreen": "#16C60C",
      "brightYellow": "#F9F1A5",
      "brightBlue": "#3B78FF",
      "brightPurple": "#B4009E",
      "brightCyan": "#61D6D6",
      "brightWhite": "#F2F2F2"
    },
    {
      "name": "Atom",
      "black": "#000000",
      "red": "#fd5ff1",
      "green": "#87c38a",
      "yellow": "#ffd7b1",
      "blue": "#85befd",
      "purple": "#b9b6fc",
      "cyan": "#85befd",
      "white": "#e0e0e0",
      "brightBlack": "#000000",
      "brightRed": "#fd5ff1",
      "brightGreen": "#94fa36",
      "brightYellow": "#f5ffa8",
      "brightBlue": "#96cbfe",
      "brightPurple": "#b9b6fc",
      "brightCyan": "#85befd",
      "brightWhite": "#e0e0e0",
      "background": "#161719",
      "foreground": "#c5c8c6"
    },
    {
      "name": "3024 Night",
      "black": "#090300",
      "red": "#db2d20",
      "green": "#01a252",
      "yellow": "#fded02",
      "blue": "#01a0e4",
      "purple": "#a16a94",
      "cyan": "#b5e4f4",
      "white": "#a5a2a2",
      "brightBlack": "#5c5855",
      "brightRed": "#e8bbd0",
      "brightGreen": "#3a3432",
      "brightYellow": "#4a4543",
      "brightBlue": "#807d7c",
      "brightPurple": "#d6d5d4",
      "brightCyan": "#cdab53",
      "brightWhite": "#f7f7f7",
      "background": "#090300",
      "foreground": "#a5a2a2"
    },
    {
      "name": "Blue Matrix",
      "black": "#101116",
      "red": "#ff5680",
      "green": "#00ff9c",
      "yellow": "#fffc58",
      "blue": "#00b0ff",
      "purple": "#d57bff",
      "cyan": "#76c1ff",
      "white": "#c7c7c7",
      "brightBlack": "#686868",
      "brightRed": "#ff6e67",
      "brightGreen": "#5ffa68",
      "brightYellow": "#fffc67",
      "brightBlue": "#6871ff",
      "brightPurple": "#d682ec",
      "brightCyan": "#60fdff",
      "brightWhite": "#ffffff",
      "background": "#101116",
      "foreground": "#00a2ff"
    },
    {
      "name": "Breeze",
      "black": "#31363b",
      "red": "#ed1515",
      "green": "#11d116",
      "yellow": "#f67400",
      "blue": "#1d99f3",
      "purple": "#9b59b6",
      "cyan": "#1abc9c",
      "white": "#eff0f1",
      "brightBlack": "#7f8c8d",
      "brightRed": "#c0392b",
      "brightGreen": "#1cdc9a",
      "brightYellow": "#fdbc4b",
      "brightBlue": "#3daee9",
      "brightPurple": "#8e44ad",
      "brightCyan": "#16a085",
      "brightWhite": "#fcfcfc",
      "background": "#31363b",
      "foreground": "#eff0f1"
    },
    {
      "name": "WildCherry",
      "black": "#000507",
      "red": "#d94085",
      "green": "#2ab250",
      "yellow": "#ffd16f",
      "blue": "#883cdc",
      "purple": "#ececec",
      "cyan": "#c1b8b7",
      "white": "#fff8de",
      "brightBlack": "#009cc9",
      "brightRed": "#da6bac",
      "brightGreen": "#f4dca5",
      "brightYellow": "#eac066",
      "brightBlue": "#308cba",
      "brightPurple": "#ae636b",
      "brightCyan": "#ff919d",
      "brightWhite": "#e4838d",
      "background": "#1f1726",
      "foreground": "#dafaff"
    },
    {
      "name": "Retro",
      "background": "#000000",
      "black": "#00ff00",
      "blue": "#00ff00",
      "brightBlack": "#00ff00",
      "brightBlue": "#00ff00",
      "brightCyan": "#00ff00",
      "brightGreen": "#00ff00",
      "brightPurple": "#00ff00",
      "brightRed": "#00ff00",
      "brightWhite": "#00ff00",
      "brightYellow": "#00ff00",
      "cyan": "#00ff00",
      "foreground": "#00ff00",
      "green": "#00ff00",
      "purple": "#00ff00",
      "red": "#00ff00",
      "white": "#00ff00",
      "yellow": "#00ff00"
    },
    {
      "name": "Raspberry",
      "background": "#3C0315",
      "black": "#282A2E",
      "blue": "#0170C5",
      "brightBlack": "#676E7A",
      "brightBlue": "#80c8ff",
      "brightCyan": "#8ABEB7",
      "brightGreen": "#B5D680",
      "brightPurple": "#AC79BB",
      "brightRed": "#BD6D85",
      "brightWhite": "#FFFFFD",
      "brightYellow": "#FFFD76",
      "cyan": "#3F8D83",
      "foreground": "#FFFFFD",
      "green": "#76AB23",
      "purple": "#7D498F",
      "red": "#BD0940",
      "white": "#FFFFFD",
      "yellow": "#E0DE48"
    }
  ],
  "keybindings": [
    {
      "command": {
        "action": "copy",
        "singleLine": false
      },
      "keys": "ctrl+c"
    },
    {
      "command": "paste",
      "keys": "ctrl+v"
    },
    {
      "command": "find",
      "keys": "ctrl+shift+f"
    },
    {
      "command": {
        "action": "splitPane",
        "split": "auto",
        "splitMode": "duplicate"
      },
      "keys": "alt+shift+d"
    }
  ]
}
